MANIFEST.in
README.rst
setup.py
mysqlbinlog2gpubsub/__init__.py
mysqlbinlog2gpubsub/config.py
mysqlbinlog2gpubsub/main.py
mysqlbinlog2gpubsub/metadata.py
mysqlbinlog2gpubsub/publishers.py
mysqlbinlog2gpubsub/pubsub.py
mysqlbinlog2gpubsub/row_event_adapter.py
mysqlbinlog2gpubsub.egg-info/PKG-INFO
mysqlbinlog2gpubsub.egg-info/SOURCES.txt
mysqlbinlog2gpubsub.egg-info/dependency_links.txt
mysqlbinlog2gpubsub.egg-info/entry_points.txt
mysqlbinlog2gpubsub.egg-info/not-zip-safe
mysqlbinlog2gpubsub.egg-info/requires.txt
mysqlbinlog2gpubsub.egg-info/top_level.txt
mysqlbinlog2gpubsub/filters/__init__.py
mysqlbinlog2gpubsub/filters/factory.py