Metadata-Version: 1.1
Name: mysqlbinlog2gpubsub
Version: 1.0.7
Summary: Send MySQL binlog event to Google Cloud Pub/Sub
Home-page: https://github.com/tarzanjw/python-mysql-binlog-pubsub
Author: Tarzan
Author-email: hoc3010@gmail.com
License: UNKNOWN
Platform: UNKNOWN
Classifier: Development Status :: 1 - Planning
Classifier: Environment :: Console
Classifier: Intended Audience :: Developers
Classifier: License :: OSI Approved :: MIT License
Classifier: Natural Language :: English
Classifier: Operating System :: OS Independent
Classifier: Programming Language :: Python :: 2.7
Classifier: Programming Language :: Python :: 3
Classifier: Programming Language :: Python :: Implementation :: PyPy
Classifier: Topic :: Documentation
Classifier: Topic :: Software Development :: Libraries :: Python Modules
Classifier: Topic :: System :: Installation/Setup
Classifier: Topic :: System :: Software Distribution
